anyim/.DS_Store
anyim/main.py
anyim/utils/dev.py
glide_text2im/__init__.py
glide_text2im/clip/__init__.py
glide_text2im/clip/attention.py
glide_text2im/clip/config.yaml
glide_text2im/clip/encoders.py
glide_text2im/clip/model_creation.py
glide_text2im/clip/utils.py
glide_text2im/download.py
glide_text2im/fp16_util.py
glide_text2im/gaussian_diffusion.py
glide_text2im/model_creation.py
glide_text2im/nn.py
glide_text2im/respace.py
glide_text2im/text2im_model.py
glide_text2im/tokenizer/__init__.py
glide_text2im/tokenizer/bpe.py
glide_text2im/tokenizer/bpe_simple_vocab_16e6.txt.gz
glide_text2im/tokenizer/encoder.json.gz
glide_text2im/tokenizer/simple_tokenizer.py
glide_text2im/tokenizer/vocab.bpe.gz
glide_text2im/unet.py
glide_text2im/xf.py
anyimage-0.1.5.dist-info/entry_points.txt
anyimage-0.1.5.dist-info/WHEEL
anyimage-0.1.5.dist-info/METADATA
anyimage-0.1.5.dist-info/RECORD
