Metadata-Version: 2.1
Name: anyimage
Version: 0.1.5
Summary: 
Author: Richard Brooker
Author-email: richard@anghami.com
Requires-Python: >=3.7,<4.0
Classifier: Programming Language :: Python :: 3
Classifier: Programming Language :: Python :: 3.10
Classifier: Programming Language :: Python :: 3.7
Classifier: Programming Language :: Python :: 3.8
Classifier: Programming Language :: Python :: 3.9
Requires-Dist: Pillow (>=8.4.0,<9.0.0)
Requires-Dist: attrs (>=21.2.0,<22.0.0)
Requires-Dist: filelock (>=3.4.2,<4.0.0)
Requires-Dist: fire (>=0.4.0,<0.5.0)
Requires-Dist: folium (==0.2.1)
Requires-Dist: ftfy (>=6.0.3,<7.0.0)
Requires-Dist: imgaug (==0.2.6)
Requires-Dist: regex (>=2021.11.10,<2022.0.0)
Requires-Dist: requests (==2.23.0)
Requires-Dist: torch (>=1.10.0,<2.0.0)
Requires-Dist: tqdm (>=4.62.3,<5.0.0)
